rapid_table_det/__init__.py
rapid_table_det/inference.py
rapid_table_det/predictor.py
rapid_table_det/models/.gitkeep
rapid_table_det/utils/__init__.py
rapid_table_det/utils/download_model.py
rapid_table_det/utils/infer_engine.py
rapid_table_det/utils/load_image.py
rapid_table_det/utils/logger.py
rapid_table_det/utils/transform.py
rapid_table_det/utils/visuallize.py
rapid_table_det-1.0.3.dist-info/LICENSE
rapid_table_det-1.0.3.dist-info/METADATA
rapid_table_det-1.0.3.dist-info/WHEEL
rapid_table_det-1.0.3.dist-info/top_level.txt
rapid_table_det-1.0.3.dist-info/RECORD
